mirai/__init__.py
mirai/adapters/__init__.py
mirai/adapters/base.py
mirai/adapters/compose.py
mirai/adapters/http.py
mirai/adapters/reverse_websocket.py
mirai/adapters/webhook.py
mirai/adapters/websocket.py
mirai/api_provider.py
mirai/asgi.py
mirai/bot.py
mirai/bot.pyi
mirai/bus.py
mirai/colorlog.py
mirai/exceptions.py
mirai/models/__init__.py
mirai/models/api.py
mirai/models/base.py
mirai/models/bus.py
mirai/models/entities.py
mirai/models/events.py
mirai/models/message.py
mirai/tasks.py
mirai/utils.py
yiri_mirai-0.2.7.dist-info/LICENSE
yiri_mirai-0.2.7.dist-info/WHEEL
yiri_mirai-0.2.7.dist-info/METADATA
yiri_mirai-0.2.7.dist-info/RECORD
