Metadata-Version: 2.1
Name: yiri-mirai
Version: 0.2.7
Summary: 一个轻量级、低耦合的基于 mirai-api-http 的 Python SDK。
Home-page: https://yiri-mirai.vercel.app
License: AGPL-3.0
Author: 忘忧北萱草
Author-email: wybxc@qq.com
Requires-Python: >=3.7,<=3.10
Classifier: License :: OSI Approved :: GNU Affero General Public License v3
Classifier: Programming Language :: Python :: 3
Classifier: Programming Language :: Python :: 3.10
Classifier: Programming Language :: Python :: 3.7
Classifier: Programming Language :: Python :: 3.8
Classifier: Programming Language :: Python :: 3.9
Provides-Extra: hypercorn
Provides-Extra: uvicorn
Requires-Dist: aiofiles (>=0.7.0,<0.8.0)
Requires-Dist: httpx (>=0.18.2,<1.0)
Requires-Dist: hypercorn (>=0.11.2,<1.0); extra == "hypercorn"
Requires-Dist: pydantic (>=1.8.2,<2.0.0)
Requires-Dist: starlette (>=0.14.2,<1.0)
Requires-Dist: typing-extensions (>=3.10.0,<4.0.0); python_version == "3.7"
Requires-Dist: uvicorn[standard] (>=0.14.0,<1.0); extra == "uvicorn"
Requires-Dist: websockets (>=10.0,<11.0)
